<?xml version="1.0" encoding="utf-8"?>
<homegearDeviceTranslation lang="en-US">
	<supportedDevices>
		<device id="FE-F6-02-01">
			<description>Rocker Switch, 2 Rocker; Light and Blind Control - Application Style 1</description>
			<longDescription>This EEP specifies a rocker switch with either 1 or 2 rockers. It can be used for F6-02-01 devices but in contrast to the default EEP supports combinations of two rockers pressed simultaneously.</longDescription>
		</device>
		<device id="FE-F6-02-02">
			<description>Rocker Switch, 2 Rocker; Light and Blind Control - Application Style 2</description>
			<longDescription>This EEP specifies a rocker switch with either 1 or 2 rockers. It can be used for F6-02-01 devices but in contrast to the default EEP supports combinations of two rockers pressed simultaneously.</longDescription>
		</device>
	</supportedDevices>
	<parameterGroups>
		<configParameters id="EnOceanConfig">
			<parameter id="ENCRYPTION">
				<label>Encryption</label>
				<description>If set to "true" Homegear enforces encryption and discards unencrypted packets from the device.</description>
			</parameter>
		</configParameters>
		<variables id="maint_ch_values">
			<parameter id="UNREACH">
				<label>Unreachable</label>
				<description>Set to "true" when the device is unreachable.</description>
			</parameter>
			<parameter id="STICKY_UNREACH">
				<label>Sticky unreachable</label>
				<description>Set to "true" when the device is unreachable. It stays "true" until reset manually.</description>
			</parameter>
			<parameter id="RSSI_DEVICE">
				<label>RSSI</label>
				<description>The RSSI of the device in dBm.</description>
			</parameter>
		</variables>
		<variables id="EnOceanVariables1">
			<parameter id="STATE">
				<label>State</label>
				<description>State of the rocker A0.</description>
			</parameter>
		</variables>
		<variables id="EnOceanVariables2">
			<parameter id="STATE">
				<label>State</label>
				<description>State of the rocker A1.</description>
			</parameter>
		</variables>
		<variables id="EnOceanVariables3">
			<parameter id="STATE">
				<label>State</label>
				<description>State of the rocker B0.</description>
			</parameter>
		</variables>
		<variables id="EnOceanVariables4">
			<parameter id="STATE">
				<label>State</label>
				<description>State of the rocker B1.</description>
			</parameter>
		</variables>
		<variables id="EnOceanVariables5">
			<parameter id="STATE">
				<label>State</label>
				<description>State of the simultaneously pressed rockers A0 and B0.</description>
			</parameter>
		</variables>
		<variables id="EnOceanVariables6">
			<parameter id="STATE">
				<label>State</label>
				<description>State of the simultaneously pressed rockers A1 and B1.</description>
			</parameter>
		</variables>
		<variables id="EnOceanVariables7">
			<parameter id="STATE">
				<label>State</label>
				<description>State of the simultaneously pressed rockers A0 and B1.</description>
			</parameter>
		</variables>
		<variables id="EnOceanVariables8">
			<parameter id="STATE">
				<label>State</label>
				<description>State of the simultaneously pressed rockers A1 and B0.</description>
			</parameter>
		</variables>
	</parameterGroups>
</homegearDeviceTranslation>
